satisfaction_config/__init__.py
satisfaction_config/config.py
take_satisfaction/__init__.py
take_satisfaction/run.py
take_satisfaction/core/__init__.py
take_satisfaction/core/calculate_satisfaction_rate.py
take_satisfaction/custom_exceptions/__init__.py
take_satisfaction/custom_exceptions/custom_exceptions.py
take_satisfaction/data_validation/__init__.py
take_satisfaction/data_validation/df_validation.py
take_satisfaction/data_validation/main.py
take_satisfaction/data_validation/run_input_validation.py
take_satisfaction/preprocess/__init__.py
take_satisfaction/preprocess/remove_manual.py
take_satisfaction/preprocess/scale_conversion.py
test/__init__.py
test/test_run.py
test/test_config/__init__.py
test/test_config/test_config.py
take_satisfaction-1.0.0.dist-info/LICENSE
take_satisfaction-1.0.0.dist-info/METADATA
take_satisfaction-1.0.0.dist-info/WHEEL
take_satisfaction-1.0.0.dist-info/top_level.txt
take_satisfaction-1.0.0.dist-info/RECORD
