Metadata-Version: 2.1
Name: take-satisfaction
Version: 1.0.0
Summary: Generate a rate between 0 and 1 for Consumer Satisfaction Survey.
Home-page: UNKNOWN
Author: squad XD
Author-email: anaytics.ped@take.net
Maintainer: Take - D&A
Maintainer-email: anaytics.ped@take.net
License: MIT License
Keywords: BLiP,score,satisfaction
Platform: UNKNOWN
Classifier: Programming Language :: Python :: 3.7
Classifier: Operating System :: OS Independent
Requires-Python: >=3.6
Requires-Dist: emoji (==0.6.0)
Requires-Dist: fuzzywuzzy (==0.18.0)
Requires-Dist: numpy (==1.19.4)
Requires-Dist: pandas (==1.1.4)
Requires-Dist: python-dateutil (==2.8.1)
Requires-Dist: pytz (==2020.4)
Requires-Dist: six (==1.15.0)
Requires-Dist: Unidecode (==1.1.1)
Requires-Dist: python-Levenshtein (==0.12.0)
